napolab/__init__.py
napolab/__main__.py
napolab/napolab.py
napolab-1.0.1.dist-info/LICENSE
napolab-1.0.1.dist-info/METADATA
napolab-1.0.1.dist-info/WHEEL
napolab-1.0.1.dist-info/entry_points.txt
napolab-1.0.1.dist-info/top_level.txt
napolab-1.0.1.dist-info/RECORD
