Metadata-Version: 2.1
Name: napolab
Version: 1.0.1
Summary: Natural Portuguese Language Benchmark
Author-email: Ruan Chaves Rodrigues <ruanchaves93@gmail.com>
License: MIT License
Project-URL: Homepage, https://github.com/ruanchaves/napolab
Keywords: ai,llm,nlp
Classifier: License :: OSI Approved :: MIT License
Classifier: Programming Language :: Python
Classifier: Programming Language :: Python :: 3
Requires-Python: >=3.9
License-File: LICENSE
Requires-Dist: datasets
Provides-Extra: dev
Requires-Dist: pytest ; extra == 'dev'
